openpile/__init__.py
openpile/construct.py
openpile/materials.py
openpile/soilmodels.py
openpile/winkler.py
openpile/core/__init__.py
openpile/core/_model_build.py
openpile/core/kernel.py
openpile/core/misc.py
openpile/core/txt.py
openpile/core/validation.py
openpile/utils/Hb_curves.py
openpile/utils/Mb_curves.py
openpile/utils/__init__.py
openpile/utils/graphics.py
openpile/utils/hooks.py
openpile/utils/misc.py
openpile/utils/mt_curves.py
openpile/utils/py_curves.py
openpile/utils/qz_curves.py
openpile/utils/tz_curves.py
openpile-1.0.2.dist-info/LICENSE.txt
openpile-1.0.2.dist-info/METADATA
openpile-1.0.2.dist-info/WHEEL
openpile-1.0.2.dist-info/top_level.txt
openpile-1.0.2.dist-info/RECORD
