Metadata-Version: 2.1
Name: openpile
Version: 1.0.2
Summary: Library for geotechnical pile calculations.
Home-page: https://github.com/TchilDill/openpile
Author: Guillaume Melin
Author-email: guillaume.melin@icloud.com
License: GPLv3
Project-URL: Documentation, https://openpile.readthedocs.io/en/latest/
Project-URL: Code, https://github.com/TchilDill/openpile
Project-URL: Issue tracker, https://github.com/TchilDill/openpile/issues
Keywords: PILE,Geotechnics,monopile,Geotechnical,calculations,PISA,winkler
Classifier: License :: OSI Approved :: GNU General Public License v3 or later (GPLv3+)
Classifier: License :: OSI Approved :: GNU General Public License v3 (GPLv3)
Classifier: Programming Language :: Python
Classifier: Programming Language :: Python :: 3.7
Classifier: Programming Language :: Python :: 3.8
Classifier: Programming Language :: Python :: 3.9
Classifier: Programming Language :: Python :: 3.10
Classifier: Operating System :: OS Independent
Requires-Python: >=3.7
License-File: LICENSE.txt
Requires-Dist: pandas
Requires-Dist: numpy<2.0
Requires-Dist: matplotlib
Requires-Dist: numba
Requires-Dist: scipy
Requires-Dist: pydantic>=2.0
Requires-Dist: typing-extensions
Provides-Extra: docs
Requires-Dist: Sphinx==5.3.0; extra == "docs"
Requires-Dist: sphinx-rtd-theme==1.3.0; extra == "docs"
Requires-Dist: sphinxcontrib-applehelp==1.0.2; extra == "docs"
Requires-Dist: sphinxcontrib-devhelp==1.0.2; extra == "docs"
Requires-Dist: sphinxcontrib-htmlhelp==2.0.0; extra == "docs"
Requires-Dist: sphinxcontrib-jsmath==1.0.1; extra == "docs"
Requires-Dist: sphinxcontrib-qthelp==1.0.3; extra == "docs"
Requires-Dist: sphinxcontrib-serializinghtml==1.1.5; extra == "docs"
Requires-Dist: sphinx-copybutton==0.5.2; extra == "docs"
Requires-Dist: autodoc-pydantic==2.0.1; extra == "docs"
Requires-Dist: pytest; extra == "docs"
Requires-Dist: pytest-cov; extra == "docs"
Requires-Dist: black==22.12.0; extra == "docs"
Requires-Dist: tox==4.4.8; extra == "docs"
